managetemplates/__init__.py
managetemplates/__main__.py
managetemplates/constants.py
managetemplates/cli_app/__init__.py
managetemplates/cli_app/fixes.py
managetemplates/cli_app/manage_templates.py
managetemplates/cli_dev/__init__.py
managetemplates/cli_dev/annotations.py
managetemplates/cli_dev/code_style.py
managetemplates/cli_dev/packaging.py
managetemplates/cli_dev/testing.py
managetemplates/cli_dev/update_readme_history.py
managetemplates/tests/__init__.py
managetemplates/tests/base.py
managetemplates/tests/test_cli.py
managetemplates/tests/test_cli_files.py
managetemplates/tests/test_doctests.py
managetemplates/tests/test_project_setup.py
managetemplates/tests/test_readme.py
managetemplates/tests/test_readme_history.py
managetemplates/utilities/__init__.py
managetemplates/utilities/cookiecutter_utils.py
managetemplates/utilities/reverse.py
managetemplates/utilities/sync_cookiecutter_templates.py
managetemplates/utilities/template_var_syntax.py
managetemplates/utilities/test_project_utils.py
managetemplates/utilities/verbose_copy.py
managetemplates-0.10.0.dist-info/METADATA
managetemplates-0.10.0.dist-info/WHEEL
managetemplates-0.10.0.dist-info/entry_points.txt
managetemplates-0.10.0.dist-info/licenses/LICENSE
managetemplates-0.10.0.dist-info/RECORD
