Metadata-Version: 2.4
Name: managetemplates
Version: 0.10.0
Summary: Pseudo Python package to test the https://github.com/jedie/cookiecutter_templates cookiecutter templates
Project-URL: Documentation, https://github.com/jedie/cookiecutter_templates
Project-URL: Source, https://github.com/jedie/cookiecutter_templates
Author-email: Jens Diemer <cookiecutter_templates@jensdiemer.de>
License: GPL-3.0-or-later
License-File: LICENSE
Requires-Python: >=3.11
Requires-Dist: bx-py-utils
Requires-Dist: cli-base-utilities
Requires-Dist: django-example
Requires-Dist: manageprojects>=0.23.0
Requires-Dist: rich
Requires-Dist: tyro
